markov_rlzoo/__init__.py
markov_rlzoo/mdp.py
markov_rlzoo/optimizers.py
markov_rlzoo/policy.py
markov_rlzoo/envs/__init__.py
markov_rlzoo/envs/gridworld.py
markov_rlzoo-0.0.1.dist-info/LICENSE
markov_rlzoo-0.0.1.dist-info/METADATA
markov_rlzoo-0.0.1.dist-info/WHEEL
markov_rlzoo-0.0.1.dist-info/top_level.txt
markov_rlzoo-0.0.1.dist-info/RECORD
