Metadata-Version: 2.1
Name: markov-rlzoo
Version: 0.0.1
Summary: Markov Decision Process Python Library
Home-page: https://github.com/rlzoo/Markov
Author: Stephen Offer
Author-email: offercstephen@example.com
License: MIT
Platform: UNKNOWN
